MANIFEST.in
README.rst
setup.cfg
setup.py
docs/HISTORY.txt
docs/LICENSE.GPL
docs/LICENSE.txt
src/collective/__init__.py
src/collective.opengraph.egg-info/PKG-INFO
src/collective.opengraph.egg-info/SOURCES.txt
src/collective.opengraph.egg-info/dependency_links.txt
src/collective.opengraph.egg-info/entry_points.txt
src/collective.opengraph.egg-info/namespace_packages.txt
src/collective.opengraph.egg-info/not-zip-safe
src/collective.opengraph.egg-info/requires.txt
src/collective.opengraph.egg-info/top_level.txt
src/collective/opengraph/__init__.py
src/collective/opengraph/browser.py
src/collective/opengraph/configure.zcml
src/collective/opengraph/events.py
src/collective/opengraph/facebook.png
src/collective/opengraph/interfaces.py
src/collective/opengraph/ogviewlet.pt
src/collective/opengraph/utils.py
src/collective/opengraph/viewlets.py
src/collective/opengraph/vocabularies.py
src/collective/opengraph/locales/collective.opengraph.pot
src/collective/opengraph/locales/rebuild.sh
src/collective/opengraph/locales/it/LC_MESSAGES/collective.opengraph.po
src/collective/opengraph/profiles/default/actions.xml
src/collective/opengraph/profiles/default/browserlayer.xml
src/collective/opengraph/profiles/default/componentregistry.xml
src/collective/opengraph/profiles/default/controlpanel.xml
src/collective/opengraph/profiles/default/metadata.xml
src/collective/opengraph/profiles/default/registry.xml
src/collective/opengraph/tests/__init__.py
src/collective/opengraph/tests/layer.py
src/collective/opengraph/tests/test_setup.py
src/collective/opengraph/tests/tests_viewlet.py
src/collective/opengraph/tests/input/test.gif