Metadata-Version: 1.0
Name: collective.opengraph
Version: 1.0.1
Summary: Plone opengraph integration
Home-page: http://plone.org/products/collective.opengraph
Author: Giorgio Borelli
Author-email: giorgio@giorgioborelli.it
License: GPL
Platform: UNKNOWN
Classifier: Framework :: Plone
Classifier: Programming Language :: Python
